autowsgr/__init__.py
autowsgr/configs.py
autowsgr/types.py
autowsgr/bin/darwin_image_autowsgrs.bin
autowsgr/bin/win32_image_autowsgrs.bin
autowsgr/constants/__init__.py
autowsgr/constants/colors.py
autowsgr/constants/custom_exceptions.py
autowsgr/constants/data_roots.py
autowsgr/constants/image_templates.py
autowsgr/constants/marker_points.py
autowsgr/constants/other_constants.py
autowsgr/constants/positions.py
autowsgr/constants/ui.py
autowsgr/data/fight_task_template.yaml
autowsgr/data/images/back_buttons/1.PNG
autowsgr/data/images/back_buttons/2.PNG
autowsgr/data/images/back_buttons/3.PNG
autowsgr/data/images/back_buttons/4.PNG
autowsgr/data/images/back_buttons/5.PNG
autowsgr/data/images/back_buttons/6.PNG
autowsgr/data/images/back_buttons/7.PNG
autowsgr/data/images/back_buttons/8.PNG
autowsgr/data/images/build_image/resource.PNG
autowsgr/data/images/build_image/equipment/complete.PNG
autowsgr/data/images/build_image/equipment/fast.PNG
autowsgr/data/images/build_image/equipment/full_depot.PNG
autowsgr/data/images/build_image/equipment/start.PNG
autowsgr/data/images/build_image/ship/complete.PNG
autowsgr/data/images/build_image/ship/fast.PNG
autowsgr/data/images/build_image/ship/full_depot.png
autowsgr/data/images/build_image/ship/start.PNG
autowsgr/data/images/chapter_image/1.PNG
autowsgr/data/images/chapter_image/2.PNG
autowsgr/data/images/chapter_image/3.PNG
autowsgr/data/images/chapter_image/4.PNG
autowsgr/data/images/chapter_image/5.PNG
autowsgr/data/images/chapter_image/6.PNG
autowsgr/data/images/chapter_image/7.PNG
autowsgr/data/images/chapter_image/8.PNG
autowsgr/data/images/chapter_image/9.PNG
autowsgr/data/images/choose_ship_image/1.PNG
autowsgr/data/images/choose_ship_image/2.PNG
autowsgr/data/images/choose_ship_image/3.PNG
autowsgr/data/images/choose_ship_image/4.png
autowsgr/data/images/confirm_image/1.PNG
autowsgr/data/images/confirm_image/2.PNG
autowsgr/data/images/confirm_image/3.PNG
autowsgr/data/images/confirm_image/4.PNG
autowsgr-1.5.7.dist-info/licenses/LICENSE
autowsgr-1.5.7.dist-info/METADATA
autowsgr-1.5.7.dist-info/WHEEL
autowsgr-1.5.7.dist-info/top_level.txt
autowsgr-1.5.7.dist-info/RECORD
