Metadata-Version: 2.4
Name: autowsgr
Version: 1.5.7
Summary: Auto Warship Girls Framework.
License: MIT
Project-URL: Homepage, https://github.com/OpenWSGR/AutoWSGR
Project-URL: Documentation, https://autowsgr.readthedocs.io/
Project-URL: Repository, https://github.com/OpenWSGR/AutoWSGR.git
Classifier: Programming Language :: Python :: 3.12
Classifier: Environment :: GPU :: NVIDIA CUDA
Classifier: Topic :: Scientific/Engineering :: Artificial Intelligence
Classifier: Topic :: System :: Distributed Computing
Requires-Python: <3.13,>=3.12
License-File: LICENSE
Requires-Dist: wheel
Requires-Dist: setuptools
Requires-Dist: rich
Requires-Dist: pre-commit
Requires-Dist: opencv-python
Requires-Dist: loguru
Requires-Dist: keyboard
Requires-Dist: easyocr>=1.7.1
Requires-Dist: airtest-openwsgr>=1.3.9
Dynamic: license-file
